{"hash":"b29b5fc397825d608148a6f54023f4f3898ebfae","data":{"gcms":{"product":{"id":"ckdu48unc0gzq0158mbzvyzg3","name":"EVGA RTX 3070 TI FTW3 ULTRA LHR 8GB GDD6X","description":"Model : 08G-P5-3797-KL\nGPU : NVIDIA GeForce RTX3070Ti\nGpu Clock : 1575 MHz (OC upto 1860 MHz)\nCUDA Core : 6144\nVideo Memory: GDDR6X 8GB\nMemory Interface: 256 bit\nMemory Clock : 19000 MHz\nBandwidth : 608 GB/s\nBus Interface : PCIe 4.0 x16\nPower Connectors : 2×8-pin\nMax Multi display : 3\nOutput: 1xHDMI 2.0b, 3xDisplayPort 1.4\nTDP : 290 W","price":48900,"images":[{"url":"https://media.graphcms.com/5mmvJohjRUOmc92FunKV"},{"url":"https://media.graphcms.com/xdJN9vGQQ6mIQ2URpFek"},{"url":"https://media.graphcms.com/eUrUawVmR26apKpspw8w"},{"url":"https://media.graphcms.com/6yL4k4txQQzH2yPV7Ktw"},{"url":"https://media.graphcms.com/FIWYwwTvSOyFRPRHij33"},{"url":"https://media.graphcms.com/OgraJmxHRMuHu31E8vTg"}]}}},"context":{"id":"ckdu48unc0gzq0158mbzvyzg3"}}